buildproj/__init__.py
buildproj/cli.py
buildproj-0.6.8.dist-info/METADATA
buildproj-0.6.8.dist-info/WHEEL
buildproj-0.6.8.dist-info/entry_points.txt
buildproj-0.6.8.dist-info/top_level.txt
buildproj-0.6.8.dist-info/RECORD
